roadmap_items/Roadmap.py
roadmap_items/RoadmapAuth.py
roadmap_items/RoadmapItem.py
roadmap_items/__init__.py
roadmap_items/cli/__init__.py
roadmap_items/cli/add_roadmap.py
roadmap_items/cli/add_roadmap_auth.py
roadmap_items/cli/add_roadmap_item.py
roadmap_items/cli/imp_roadmap.py
roadmap_items/cli/imp_roadmap_auth.py
roadmap_items/cli/imp_roadmap_item.py
roadmap_items/cli/search_roadmap.py
roadmap_items/cli/search_roadmap_item.py
roadmap_items-0.3.12.data/data/spec/roadmap_items.yaml
roadmap_items-0.3.12.dist-info/METADATA
roadmap_items-0.3.12.dist-info/WHEEL
roadmap_items-0.3.12.dist-info/entry_points.txt
roadmap_items-0.3.12.dist-info/top_level.txt
roadmap_items-0.3.12.dist-info/RECORD
