Metadata-Version: 2.1
Name: roadmap-items
Version: 0.3.12
Summary: Roadmap service to manage roadmaps and roadmap items with RBAC
Home-page: https://wittlesouth.com:32002/projects/RFTW/repos/roadmap_items/browse
Author: Wittle South Ventures, LLC
Author-email: eric@wittlesouth.com
License: UNKNOWN
Platform: UNKNOWN
Classifier: License :: Other/Proprietary License
Classifier: Intended Audience :: Developers
Classifier: Topic :: Software Development :: Libraries
Requires-Dist: coverage
Requires-Dist: nose
Requires-Dist: PyYAML
Requires-Dist: smoacks
